threed_optix/__init__.py
threed_optix/analyses.py
threed_optix/beams.py
threed_optix/client.py
threed_optix/optimize.py
threed_optix/parts.py
threed_optix/simulations.py
threed_optix/utils.py
threed_optix/package_utils/__init__.py
threed_optix/package_utils/api.py
threed_optix/package_utils/general.py
threed_optix/package_utils/math.py
threed_optix/package_utils/matlab.py
threed_optix/package_utils/vars.py
threed_optix/package_utils/verifiers.py
threed_optix-5.0.32.dist-info/LICENSE.txt
threed_optix-5.0.32.dist-info/METADATA
threed_optix-5.0.32.dist-info/WHEEL
threed_optix-5.0.32.dist-info/top_level.txt
threed_optix-5.0.32.dist-info/RECORD
