Metadata-Version: 2.1
Name: threed_optix
Version: 5.0.32
Home-page: https://3doptix.com
Author: 3DOptix
Author-email: ereztep@3doptix.com
License: MIT
Keywords: Optics,Optical Design,Optical Simulation,Optical Design Software,3DOptix
License-File: LICENSE.txt
Requires-Dist: requests
Requires-Dist: pandas
Requires-Dist: matplotlib
Requires-Dist: plotly
Requires-Dist: colorama
Requires-Dist: nbformat
Requires-Dist: numpy
Requires-Dist: scikit-image
Requires-Dist: scipy
Requires-Dist: opencv-python
Requires-Dist: dill
Requires-Dist: ply
Requires-Dist: networkx
Requires-Dist: pytest
Requires-Dist: typeguard
